lowtran/CMakeLists.txt
lowtran/__init__.py
lowtran/base.py
lowtran/cmake.py
lowtran/plot.py
lowtran/scenarios.py
lowtran/cmake/compilers.cmake
lowtran/cmake/f2py.cmake
lowtran/cmake/f2pyTarget.cmake
lowtran/cmake/options.cmake
lowtran/fortran/lowtran7.f
lowtran/tests/test_horiz.py
lowtran/tests/test_mod.py
lowtran/tests/test_scenarios.py
lowtran-3.1.0.dist-info/LICENSE.txt
lowtran-3.1.0.dist-info/METADATA
lowtran-3.1.0.dist-info/WHEEL
lowtran-3.1.0.dist-info/top_level.txt
lowtran-3.1.0.dist-info/RECORD
