Metadata-Version: 2.1
Name: lowtran
Version: 3.1.0
Summary: Model of Earth atmosphere absorption and transmission vs. wavelength and location.
Keywords: mesosphere,stratosphere,thermosphere,atmosphere
Classifier: Development Status :: 4 - Beta
Classifier: Environment :: Console
Classifier: Operating System :: OS Independent
Classifier: Programming Language :: Python :: 3
Classifier: Intended Audience :: Science/Research
Classifier: Programming Language :: Fortran
Classifier: Topic :: Scientific/Engineering :: Atmospheric Science
Requires-Python: >=3.8
License-File: LICENSE.txt
Requires-Dist: numpy
Requires-Dist: xarray
Requires-Dist: python-dateutil
Provides-Extra: lint
Requires-Dist: flake8 ; extra == 'lint'
Requires-Dist: flake8-bugbear ; extra == 'lint'
Requires-Dist: flake8-builtins ; extra == 'lint'
Requires-Dist: flake8-blind-except ; extra == 'lint'
Requires-Dist: mypy ; extra == 'lint'
Requires-Dist: types-python-dateutil ; extra == 'lint'
Provides-Extra: tests
Requires-Dist: pytest ; extra == 'tests'
